numpyds/__init__.py
numpyds/main.py
numpyds-3.2.dist-info/METADATA
numpyds-3.2.dist-info/WHEEL
numpyds-3.2.dist-info/top_level.txt
numpyds-3.2.dist-info/RECORD
