Metadata-Version: 2.1
Name: numpyds
Version: 3.2
Summary: NumPy library for Data science
Author-email: officialnumpy@gmail.com
